confset/__init__.py
confset/__main__.py
confset/arguments.py
confset/cli.py
confset/confset.py
confset/debug.py
confset/metadata.py
confset/package_metadata.json
confset-0.1.0.dist-info/LICENSE.txt
confset-0.1.0.dist-info/METADATA
confset-0.1.0.dist-info/WHEEL
confset-0.1.0.dist-info/entry_points.txt
confset-0.1.0.dist-info/top_level.txt
confset-0.1.0.dist-info/RECORD
