Metadata-Version: 2.1
Name: confset
Version: 0.1.0
Summary: A simple script to change or update package configurations
Home-page: https://github.com/dwighthubbard/confset
Author: Dwight Hubbard
Author-email: 254983+dwighthubbard@users.noreply.github.com
License: Apache 2.0
Project-URL: Source, https://github.com/dwighthubbard/confset
Platform: UNKNOWN
Classifier: License :: OSI Approved :: Apache Software License
Classifier: Development Status :: 4 - Beta
Classifier: Environment :: Console
Classifier: Intended Audience :: Developers
Classifier: Operating System :: MacOS :: MacOS X
Classifier: Operating System :: POSIX :: BSD :: FreeBSD
Classifier: Operating System :: POSIX :: Linux
Classifier: Operating System :: POSIX :: SunOS/Solaris
Classifier: Operating System :: POSIX
Classifier: Programming Language :: Python :: 3.6
Classifier: Programming Language :: Python :: 3.7
Classifier: Programming Language :: Python :: 3.8
Classifier: Programming Language :: Python :: Implementation :: CPython
Classifier: Topic :: System :: Systems Administration
Classifier: Topic :: Utilities
Requires: configobj
Requires-Python: >=3.5
